{"asof":"2026-07-14T23:37:14+00:00","count":20,"missing":[],"companies":{"NVDA":{"price":211.8,"ma50":209.0846,"ma200":191.79594,"yearHigh":236.54,"yearLow":164.07,"fwd_eps":8.98,"fwd_growth":41.0},"TSM":{"price":420.39,"ma50":424.5066,"ma200":349.02484,"yearHigh":479,"yearLow":223.7,"fwd_eps":504.23,"fwd_growth":28.8},"AVGO":{"price":389.11,"ma50":406.0224,"ma200":362.67206,"yearHigh":495,"yearLow":273,"fwd_eps":11.57,"fwd_growth":68.0},"FIX":{"price":1775.1,"ma50":1882.8458,"ma200":1335.4017,"yearHigh":2073.99,"yearLow":513.99,"fwd_eps":43.63,"fwd_growth":24.2},"ETN":{"price":415.52,"ma50":405.4056,"ma200":372.35565,"yearHigh":436.74,"yearLow":311.92,"fwd_eps":13.35,"fwd_growth":17.8},"HEI":{"price":345.61,"ma50":322.0332,"ma200":315.7897,"yearHigh":369.48,"yearLow":256.11,"fwd_eps":6.1,"fwd_growth":12.8},"TDG":{"price":1215.34,"ma50":1249.9056,"ma200":1284.6344,"yearHigh":1623.83,"yearLow":1123.61,"fwd_eps":40.04,"fwd_growth":17.3},"HWM":{"price":276.78,"ma50":263.5278,"ma200":230.08804,"yearHigh":290.63,"yearLow":169.45,"fwd_eps":5.06,"fwd_growth":19.6},"SPGI":{"price":438.87,"ma50":400.75165,"ma200":436.54373,"yearHigh":547.82404,"yearLow":361.03122,"fwd_eps":18.6,"fwd_growth":12.0},"MCO":{"price":494.73,"ma50":455.6168,"ma200":471.10114,"yearHigh":546.88,"yearLow":402.28,"fwd_eps":16.74,"fwd_growth":11.5},"MSCI":{"price":611.43,"ma50":593.2138,"ma200":570.7009,"yearHigh":644.68,"yearLow":501.08,"fwd_eps":19.82,"fwd_growth":14.7},"TJX":{"price":150.35,"ma50":156.5374,"ma200":153.4878,"yearHigh":170,"yearLow":119.84,"fwd_eps":5.23,"fwd_growth":10.2},"ROST":{"price":220.93,"ma50":224.1176,"ma200":196.34355,"yearHigh":242.81,"yearLow":126.32,"fwd_eps":7.82,"fwd_growth":10.2},"BURL":{"price":334.31,"ma50":317.4006,"ma200":299.47156,"yearHigh":351.85,"yearLow":240.49,"fwd_eps":11.81,"fwd_growth":16.3},"ISRG":{"price":379.5,"ma50":423.025,"ma200":487.79184,"yearHigh":603.88,"yearLow":378.5,"fwd_eps":10.44,"fwd_growth":13.4},"SYK":{"price":311.21,"ma50":309.3992,"ma200":346.0733,"yearHigh":404.87,"yearLow":281,"fwd_eps":14.98,"fwd_growth":11.6},"GMED":{"price":75.82,"ma50":81.0054,"ma200":82.54225,"yearHigh":101.4,"yearLow":51.79,"fwd_eps":4.74,"fwd_growth":8.6},"WM":{"price":234.27,"ma50":221.3892,"ma200":221.99185,"yearHigh":248.13,"yearLow":194.11,"fwd_eps":8.15,"fwd_growth":12.4},"RSG":{"price":220.03,"ma50":209.181,"ma200":215.0415,"yearHigh":246.25,"yearLow":196.41,"fwd_eps":7.28,"fwd_growth":10.8},"WCN":{"price":169.57,"ma50":158.5206,"ma200":166.33266,"yearHigh":191.91,"yearLow":146.89,"fwd_eps":5.4,"fwd_growth":12.3}}}